infrahealth/__init__.py
infrahealth/alert.py
infrahealth/cli.py
infrahealth/docker_health.py
infrahealth/health.py
infrahealth/prometheus_exporter.py
tests/__init__.py
tests/test_docker_health.py
tests/test_health.py
infrahealth-0.1.0.dist-info/METADATA
infrahealth-0.1.0.dist-info/WHEEL
infrahealth-0.1.0.dist-info/entry_points.txt
infrahealth-0.1.0.dist-info/top_level.txt
infrahealth-0.1.0.dist-info/RECORD
