Metadata-Version: 2.4
Name: infrahealth
Version: 0.1.0
Summary: A CLI for monitoring server and Docker container health
Home-page: https://github.com/usmansafdarktk/infrahealth.git
Author: Muhammad Usman Safder
Author-email: usmansafderktk@gmail.com
License: MIT
Classifier: Programming Language :: Python :: 3
Classifier: License :: OSI Approved :: MIT License
Classifier: Operating System :: OS Independent
Requires-Python: >=3.6
Requires-Dist: click
Requires-Dist: psutil
Requires-Dist: docker
Requires-Dist: requests
Requires-Dist: prometheus_client
Dynamic: author
Dynamic: author-email
Dynamic: classifier
Dynamic: description
Dynamic: description-content-type
Dynamic: home-page
Dynamic: license
Dynamic: requires-dist
Dynamic: requires-python
Dynamic: summary
